b3api/__init__.py
b3api/__main__.py
b3api/assets.py
b3api-0.0.4.dist-info/METADATA
b3api-0.0.4.dist-info/WHEEL
b3api-0.0.4.dist-info/top_level.txt
b3api-0.0.4.dist-info/RECORD
