Metadata-Version: 2.1
Name: b3api
Version: 0.0.4
Summary: Uma biblioteca simples para consumir dados de ativos da bolsa de valores brasileira, B3.
Home-page: https://github.com/mariotaddeucci/packages/python/b3api/
Author: Mario Taddeucci
Author-email: mariotaddeucci@gmx.com
License: MIT
Platform: UNKNOWN
Classifier: Programming Language :: Python :: 3
Classifier: License :: OSI Approved :: MIT License
Classifier: Operating System :: OS Independent
Requires-Dist: requests (>=2.25.1)
